database_automation/__init__.py
database_automation/mongo_crud.py
MongoDB_Connect_Petar-0.0.4.dist-info/LICENSE
MongoDB_Connect_Petar-0.0.4.dist-info/METADATA
MongoDB_Connect_Petar-0.0.4.dist-info/WHEEL
MongoDB_Connect_Petar-0.0.4.dist-info/top_level.txt
MongoDB_Connect_Petar-0.0.4.dist-info/RECORD
